retry_function_plugin/__init__.py
retry_function_plugin/retry_function.py
retry_function_plugin-0.1.0.dist-info/METADATA
retry_function_plugin-0.1.0.dist-info/WHEEL
retry_function_plugin-0.1.0.dist-info/top_level.txt
retry_function_plugin-0.1.0.dist-info/RECORD
