Metadata-Version: 2.4
Name: retry-function-plugin
Version: 0.1.0
Summary: A reusable async retry handler with exponential backoff and structured logging.
Author: Sivaranjani Palanivel
License: MIT
Project-URL: Homepage, https://pypi.org/project/retry-function-plugin/
Requires-Python: >=3.8
